donkeycar/__init__.py
donkeycar/config.py
donkeycar/geom.py
donkeycar/la.py
donkeycar/memory.py
donkeycar/utils.py
donkeycar/vehicle.py
donkeycar/benchmarks/tub.py
donkeycar/benchmarks/tub_v2.py
donkeycar/contrib/__init__.py
donkeycar/contrib/robohat/code-robocarstore.py
donkeycar/contrib/robohat/code.py
donkeycar/contrib/robohat/rear_light.py
donkeycar/gym/__init__.py
donkeycar/gym/gym_real.py
donkeycar/gym/remote_controller.py
donkeycar/management/__init__.py
donkeycar/management/base.py
donkeycar/management/graph.py
donkeycar/management/joystick_creator.py
donkeycar/management/makemovie.py
donkeycar/management/tub_web/base.html
donkeycar/management/tub_web/tub.html
donkeycar/management/tub_web/tubs.html
donkeycar/management/ui/__init__.py
donkeycar/management/ui/car_screen.kv
donkeycar/management/ui/car_screen.py
donkeycar/management/ui/common.kv
donkeycar/management/ui/common.py
donkeycar/management/ui/pilot_screen.kv
donkeycar/management/ui/pilot_screen.py
donkeycar/management/ui/rc_file_handler.py
donkeycar/management/ui/train_screen.kv
donkeycar/management/ui/train_screen.py
donkeycar/management/ui/tub_screen.kv
donkeycar/management/ui/tub_screen.py
donkeycar/management/ui/ui.kv
donkeycar/management/ui/ui.py
donkeycar/parts/__init__.py
donkeycar/parts/actuator.py
donkeycar/parts/behavior.py
donkeycar/parts/camera.py
donkeycar/parts/controller.py
donkeycar/parts/coral.py
donkeycar/parts/cv.py
donkeycar/parts/datastore.py
donkeycar/parts/datastore_v2.py
donkeycar/parts/dgym.py
donkeycar/parts/encoder.py
donkeycar/parts/explode.py
donkeycar/parts/fast_stretch.py
donkeycar/parts/fastai.py
donkeycar/parts/file_watcher.py
donkeycar/parts/fps.py
donkeycar/parts/gps.py
donkeycar/parts/graph.py
donkeycar/parts/image.py
donkeycar/parts/image_transformations.py
donkeycar/parts/imu.py
donkeycar/parts/interpreter.py
donkeycar/parts/keras.py
donkeycar/parts/kinematics.py
donkeycar/parts/launch.py
donkeycar/parts/led_status.py
donkeycar/parts/leopard_imaging.py
donkeycar-5.2.0.dist-info/licenses/LICENSE
donkeycar-5.2.0.dist-info/METADATA
donkeycar-5.2.0.dist-info/WHEEL
donkeycar-5.2.0.dist-info/entry_points.txt
donkeycar-5.2.0.dist-info/top_level.txt
donkeycar-5.2.0.dist-info/zip-safe
donkeycar-5.2.0.dist-info/RECORD
