Metadata-Version: 2.4
Name: donkeycar
Version: 5.2.0
Summary: Self driving library for python.
Home-page: https://github.com/autorope/donkeycar
Author: Will Roscoe, Adam Conway, Tawn Kramer
License: MIT
Keywords: selfdriving cars donkeycar diyrobocars
Classifier: Development Status :: 4 - Beta
Classifier: Intended Audience :: Developers
Classifier: Topic :: Scientific/Engineering :: Artificial Intelligence
Classifier: Programming Language :: Python :: 3.11
Requires-Python: <3.12,>=3.11.0
License-File: LICENSE
Requires-Dist: numpy
Requires-Dist: pillow
Requires-Dist: docopt
Requires-Dist: tornado
Requires-Dist: requests
Requires-Dist: PrettyTable
Requires-Dist: paho-mqtt
Requires-Dist: simple_pid
Requires-Dist: progress
Requires-Dist: pyfiglet
Requires-Dist: psutil
Requires-Dist: pynmea2
Requires-Dist: pyserial
Requires-Dist: utm
Requires-Dist: pandas
Requires-Dist: pyyaml
Provides-Extra: pi
Requires-Dist: picamera2; extra == "pi"
Requires-Dist: Adafruit_PCA9685; extra == "pi"
Requires-Dist: adafruit-circuitpython-ssd1306; extra == "pi"
Requires-Dist: adafruit-circuitpython-rplidar; extra == "pi"
Requires-Dist: RPi.GPIO; extra == "pi"
Requires-Dist: flatbuffers==24.3.*; extra == "pi"
Requires-Dist: tensorflow-aarch64==2.15.*; extra == "pi"
Requires-Dist: opencv-contrib-python; extra == "pi"
Requires-Dist: matplotlib; extra == "pi"
Requires-Dist: kivy; extra == "pi"
Requires-Dist: kivy-garden.matplotlib; extra == "pi"
Requires-Dist: pandas; extra == "pi"
Requires-Dist: plotly; extra == "pi"
Requires-Dist: albumentations; extra == "pi"
Provides-Extra: nano
Requires-Dist: Adafruit_PCA9685; extra == "nano"
Requires-Dist: adafruit-circuitpython-ssd1306; extra == "nano"
Requires-Dist: adafruit-circuitpython-rplidar; extra == "nano"
Requires-Dist: Jetson.GPIO; extra == "nano"
Requires-Dist: numpy==1.23.*; extra == "nano"
Requires-Dist: matplotlib==3.7.*; extra == "nano"
Requires-Dist: kivy; extra == "nano"
Requires-Dist: kivy-garden.matplotlib; extra == "nano"
Requires-Dist: plotly; extra == "nano"
Requires-Dist: pandas==2.0.*; extra == "nano"
Provides-Extra: pc
Requires-Dist: tensorflow==2.15.*; extra == "pc"
Requires-Dist: matplotlib; extra == "pc"
Requires-Dist: kivy; extra == "pc"
Requires-Dist: kivy-garden.matplotlib; extra == "pc"
Requires-Dist: pandas; extra == "pc"
Requires-Dist: plotly; extra == "pc"
Requires-Dist: albumentations; extra == "pc"
Provides-Extra: macos
Requires-Dist: tensorflow==2.15.*; extra == "macos"
Requires-Dist: tensorflow-metal; extra == "macos"
Requires-Dist: matplotlib; extra == "macos"
Requires-Dist: kivy; extra == "macos"
Requires-Dist: kivy-garden.matplotlib; extra == "macos"
Requires-Dist: pandas; extra == "macos"
Requires-Dist: plotly; extra == "macos"
Requires-Dist: albumentations; extra == "macos"
Provides-Extra: dev
Requires-Dist: pytest; extra == "dev"
Requires-Dist: pytest-cov; extra == "dev"
Requires-Dist: responses; extra == "dev"
Requires-Dist: mypy; extra == "dev"
Provides-Extra: torch
Requires-Dist: torch==2.1.*; extra == "torch"
Requires-Dist: pytorch-lightning; extra == "torch"
Requires-Dist: torchvision; extra == "torch"
Requires-Dist: torchaudio; extra == "torch"
Requires-Dist: fastai; extra == "torch"
Dynamic: license-file
